locsum/__init__.py
locsum/config.toml
locsum/main.py
locsum/pdf.css
locsum-0.2.0.dist-info/METADATA
locsum-0.2.0.dist-info/WHEEL
locsum-0.2.0.dist-info/entry_points.txt
locsum-0.2.0.dist-info/licenses/LICENSE
locsum-0.2.0.dist-info/RECORD
