Metadata-Version: 2.4
Name: locsum
Version: 0.2.0
Summary: Terminal tool for offline transcription and summarization of audio/video files.
Project-URL: Repository, https://github.com/monsieurlinux/locsum
Author-email: Monsieur Linux <info@mlinux.ca>
License-Expression: MIT
License-File: LICENSE
Keywords: ai,cli,gpu,llm,privacy,python,self-hosted,youtube
Classifier: Operating System :: OS Independent
Classifier: Programming Language :: Python :: 3
Requires-Python: >=3.11
Requires-Dist: markdown-it-py<5.0.0,>=3.0.0
Requires-Dist: ollama<1.0.0,>=0.6.1
Requires-Dist: openai-whisper>=20250625
Requires-Dist: weasyprint>=68.0
